osmnet/__init__.py
osmnet/config.py
osmnet/load.py
osmnet/utils.py
osmnet-0.1.7.dist-info/LICENSE.txt
osmnet-0.1.7.dist-info/METADATA
osmnet-0.1.7.dist-info/WHEEL
osmnet-0.1.7.dist-info/top_level.txt
osmnet-0.1.7.dist-info/RECORD
