Metadata-Version: 2.1
Name: osmnet
Version: 0.1.7
Summary: Tools for the extraction of OpenStreetMap street network data for use in Pandana accessibility analyses.
Home-page: https://github.com/UDST/osmnet
Author: UrbanSim Inc.
License: AGPL
Classifier: Intended Audience :: Science/Research
Classifier: Topic :: Scientific/Engineering :: Information Analysis
Classifier: Programming Language :: Python :: 3
Classifier: Programming Language :: Python :: 3.8
Classifier: Programming Language :: Python :: 3.9
Classifier: Programming Language :: Python :: 3.10
Classifier: Programming Language :: Python :: 3.11
Classifier: Development Status :: 3 - Alpha
Classifier: License :: OSI Approved :: GNU Affero General Public License v3
Requires-Python: >=3
License-File: LICENSE.txt
Requires-Dist: geopandas (>=0.11)
Requires-Dist: numpy (>=1.10)
Requires-Dist: pandas (>=0.23)
Requires-Dist: requests (>=2.9.1)
Requires-Dist: shapely (>=1.8)
